Pyjo/__init__.py
Pyjo/Reactor/Asyncio.py
Pyjo/Reactor/__init__.py
Pyjo_Reactor_Asyncio-0.0.1.dist-info/DESCRIPTION.rst
Pyjo_Reactor_Asyncio-0.0.1.dist-info/METADATA
Pyjo_Reactor_Asyncio-0.0.1.dist-info/RECORD
Pyjo_Reactor_Asyncio-0.0.1.dist-info/WHEEL
Pyjo_Reactor_Asyncio-0.0.1.dist-info/metadata.json
Pyjo_Reactor_Asyncio-0.0.1.dist-info/top_level.txt
Pyjo_Reactor_Asyncio-0.0.1.dist-info/zip-safe
