Metadata-Version: 2.0
Name: Pyjo-Reactor-Asyncio
Version: 0.0.1
Summary: Low level event reactor for Pyjoyment with asyncio support.
Home-page: http://github.com/dex4er/Pyjo-Reactor-Asyncio
Author: Piotr Roszatycki
Author-email: piotr.roszatycki@gmail.com
License: Artistic
Download-URL: https://github.com/dex4er/Pyjo-Reactor-Asyncio/archive/master.zip
Keywords: async asyncio mojo mojolicious pyjo pyjoyment reactor
Platform: UNKNOWN
Classifier: Development Status :: 2 - Pre-Alpha
Classifier: Environment :: Web Environment
Classifier: Intended Audience :: Developers
Classifier: License :: OSI Approved :: Artistic License
Classifier: Operating System :: OS Independent
Classifier: Programming Language :: Python
Classifier: Programming Language :: Python :: 2.7
Classifier: Programming Language :: Python :: 3.3
Classifier: Programming Language :: Python :: 3.4
Classifier: Programming Language :: Python :: 3.5
Requires-Dist: Pyjoyment
Requires-Dist: trollius; python_version < "3.0"
Requires-Dist: asyncio; python_version >= "3.0" and python_version < "3.4"
